{
  "sections": {
    "main": {
      "type": "main-list-collections",
      "settings": {
        "title": "Collections",
        "sort": "alphabetical",
        "image_ratio": "square",
        "columns_desktop": 3,
        "columns_mobile": "2"
      }
    },
    "1663532004d08e7f61": {
      "type": "featured-collection",
      "settings": {
        "title": "Featured collections",
        "heading_size": "h1",
        "description": "",
        "show_description": false,
        "description_style": "body",
        "collection": "frontpage",
        "products_to_show": 8,
        "columns_desktop": 3,
        "full_width": false,
        "show_view_all": true,
        "view_all_style": "solid",
        "enable_desktop_slider": false,
        "color_scheme": "background-1",
        "image_ratio": "adapt",
        "show_secondary_image": false,
        "show_vendor": false,
        "show_rating": false,
        "enable_quick_add": false,
        "columns_mobile": "2",
        "swipe_on_mobile": false,
        "padding_top": 36,
        "padding_bottom": 36
      }
    }
  },
  "order": [
    "main",
    "1663532004d08e7f61"
  ]
}